README.md
setup.py
bin/slitfinder.py
bin/z_widget.py
broadreduce/__init__.py
broadreduce/binning.py
broadreduce/cleaning.py
broadreduce/distortion.py
broadreduce/pipeline.py
broadreduce/preprocessing.py
broadreduce/skysub.py
broadreduce/slits.py
broadreduce/spec_1D.py
broadreduce/utils.py
broadreduce/wave_soln.py
broadreduce.egg-info/PKG-INFO
broadreduce.egg-info/SOURCES.txt
broadreduce.egg-info/dependency_links.txt
broadreduce.egg-info/requires.txt
broadreduce.egg-info/top_level.txt