Metadata-Version: 2.1
Name: broadreduce
Version: 1.0.2
Summary: Spectra reduction pipeline for broad-slit spectroscopy (Tuned for Keck LRIS).
Home-page: https://github.com/HSouch/broadreduce
Author: Harrison Souchereau
Author-email: harrison.souchereau@yale.edu
License: BSD-3-Clause
Keywords: galaxies spectra spectroscopy
Classifier: Development Status :: 4 - Beta
Classifier: Intended Audience :: Developers
Classifier: Topic :: Software Development :: Build Tools
Classifier: Programming Language :: Python :: 3.6
Classifier: Programming Language :: Python :: 3.7
Classifier: Programming Language :: Python :: 3.8
